{"_ts":[1493618890,1493662750],"_r":{"breakdown":{"html":{"bytes":[22849,39937],"requests":[2,3]},"js":{"bytes":[247984,262158],"requests":[36,36]},"css":{"bytes":[92940,98667],"requests":[16,16]},"image":{"bytes":[5536113,5551282],"requests":[29,29]},"flash":{"bytes":[0,0],"requests":[0,0]},"font":{"bytes":[138299,146390],"requests":[6,6]},"other":{"bytes":[0,0],"requests":[0,0]}},"date":[1493618890,1493662750],"domElements":[534,534],"domInteractive":[3881,3287],"firstPaint":[3847,3264],"fullyLoaded":[15834,12963],"id":["170501_6X_B28","170501_46_10VZ"],"loadTime":[13090,12466],"render":[4390,3889],"SpeedIndex":[6862,6811],"TTFB":[4930,1788],"videoFrames":[[{"_i":"frame_0000.jpg","_t":0,"_vc":0},{"_i":"frame_0044.jpg","_t":4400,"_vc":1},{"_i":"frame_0047.jpg","_t":4700,"_vc":6},{"_i":"frame_0048.jpg","_t":4800,"_vc":47},{"_i":"frame_0053.jpg","_t":5300,"_vc":50},{"_i":"frame_0060.jpg","_t":6000,"_vc":55},{"_i":"frame_0063.jpg","_t":6300,"_vc":58},{"_i":"frame_0088.jpg","_t":8800,"_vc":80},{"_i":"frame_0099.jpg","_t":9900,"_vc":97},{"_i":"frame_0116.jpg","_t":11600,"_vc":100}],[{"_i":"frame_0000.jpg","_t":0,"_vc":0},{"_i":"frame_0039.jpg","_t":3900,"_vc":1},{"_i":"frame_0041.jpg","_t":4100,"_vc":6},{"_i":"frame_0044.jpg","_t":4400,"_vc":47},{"_i":"frame_0047.jpg","_t":4700,"_vc":49},{"_i":"frame_0049.jpg","_t":4900,"_vc":49},{"_i":"frame_0052.jpg","_t":5200,"_vc":55},{"_i":"frame_0054.jpg","_t":5400,"_vc":58},{"_i":"frame_0086.jpg","_t":8600,"_vc":65},{"_i":"frame_0097.jpg","_t":9700,"_vc":85},{"_i":"frame_0106.jpg","_t":10600,"_vc":97},{"_i":"frame_0127.jpg","_t":12700,"_vc":100}]],"visualComplete":[11600,12700],"lighthouse":[null,null],"pagespeed":[19,20]}}